{
  "start_date": "2026-07-14",
  "start_capital": 100000000,
  "currency": "KRW",
  "cash": 56398258,
  "holdings": {
    "GC=F": {
      "name": "금",
      "qty": 1.9907879076675754,
      "cost_krw": 12000000.0,
      "lots": [
        {
          "date": "2026-07-14",
          "session": "us",
          "qty": 1.9908,
          "price_krw": 6027764,
          "price_native": 4034.0,
          "currency": "USD",
          "krw": 12000000,
          "fx": 1494.24,
          "price_date": "2026-07-14",
          "basis": "즉시(24h)"
        }
      ]
    },
    "XLV": {
      "name": "헬스케어ETF",
      "qty": 50.0,
      "cost_krw": 11882199.48,
      "lots": [
        {
          "date": "2026-07-15",
          "session": "us",
          "qty": 50,
          "price_krw": 237644,
          "price_native": 159.78,
          "currency": "USD",
          "krw": 11882199,
          "fx": 1487.32,
          "price_date": "2026-07-14",
          "basis": "2026-07-14 개장 시가"
        }
      ]
    },
    "XLF": {
      "name": "금융ETF",
      "qty": 120.0,
      "cost_krw": 9923399.04,
      "lots": [
        {
          "date": "2026-07-15",
          "session": "us",
          "qty": 120,
          "price_krw": 82695,
          "price_native": 55.6,
          "currency": "USD",
          "krw": 9923399,
          "fx": 1487.32,
          "price_date": "2026-07-14",
          "basis": "2026-07-14 개장 시가"
        }
      ]
    },
    "AAPL": {
      "name": "애플",
      "qty": 21.0,
      "cost_krw": 9796143.9408,
      "lots": [
        {
          "date": "2026-07-15",
          "session": "us",
          "qty": 21,
          "price_krw": 466483,
          "price_native": 313.64,
          "currency": "USD",
          "krw": 9796144,
          "fx": 1487.32,
          "price_date": "2026-07-14",
          "basis": "2026-07-14 개장 시가"
        }
      ]
    }
  },
  "applied_orders": [
    "2026-07-14-us-stable",
    "2026-07-15-kr-stable"
  ],
  "pending_orders": [
    {
      "placed_date": "2026-07-15",
      "session": "kr",
      "action": "buy",
      "ticker": "207940.KS",
      "name": "삼성바이오로직스",
      "krw": 8000000,
      "qty": null,
      "reason": "장기 계약 기반으로 이익이 꾸준한 국내 대표 방어 헬스케어 대형주. 오늘 -2.3%로 약세, 52주 고점 대비 -30%로 가격 메리트 구간이며 RSI 48.6으로 과열도 아니다. 반등을 추격하는 게 아니라 우량 방어주를 눌림에 담는 가치 접근 — 총자산 8%, 정수 5주 내외로 시작.",
      "min_fill_date": "2026-07-15"
    }
  ],
  "journal": [
    {
      "date": "2026-07-14",
      "session": "us",
      "comment": "CPI 대기 밤 — 풀매수 금지. 방어자산(금·헬스케어)과 실적 확인된 가치(금융)·우량 대형주만 소액 분산, 현금 56% 방패 유지.",
      "placed": [
        {
          "action": "매수예약",
          "name": "헬스케어ETF",
          "detail": "12,000,000원 · 다음 개장 시가 체결 대기 — 이익이 꾸준하고 경기·금리 민감도가 낮은 대표 방어 섹터. 반도체 쇼크가 국경 없이 번지는 장세에서 기술 대신 필수 수요주로 변동성을 낮춘다. ETF라 단일종목 리스크도 분산. 12%."
        },
        {
          "action": "매수예약",
          "name": "금융ETF",
          "detail": "10,000,000원 · 다음 개장 시가 체결 대기 — JPM(EPS $6.14, 컨센 $5.85 대폭 상회)·WFC 실적 서프라이즈로 이익 모멘텀이 확인된 가치 섹터. 금리 급등이 NIM에 우호적이라 CPI가 뜨거워도 방어된다. 개별주 대신 ETF로 안전하게. 10%."
        },
        {
          "action": "매수예약",
          "name": "애플",
          "detail": "10,000,000원 · 다음 개장 시가 체결 대기 — 재무가 탄탄하고 현금흐름이 꾸준한 초우량 대형주. 반도체·고베타 성장주가 밀린 날에도 +0.63%로 상대적 방어력을 보였다. 추격이 아닌 우량주 편입 차원의 소액 진입. 10%."
        },
        {
          "action": "유지",
          "name": "-",
          "detail": "엔비디아·AMD·SMH 등 급락 반도체와 XLE(에너지 +3% 급등)는 모멘텀·고변동 구간이라 안정형 원칙상 신규 진입 회피. 나머지 56%는 21:30 CPI 코어 확인 후 방향이 서면 집행할 현금으로 남긴다."
        }
      ],
      "trades": [
        {
          "action": "매수",
          "ticker": "GC=F",
          "name": "금",
          "krw": 12000000,
          "krw_str": "12,000,000",
          "qty": 1.9908,
          "price_krw": 6027764,
          "basis": "즉시(24h)",
          "reason": "유가·구리·금 동반 상승의 리플레이션·지정학 프리미엄 국면. VIX 17.5로 언제든 튈 수 있는 이벤트(21:30 CPI) 앞에서 금은 순수 방패다. 즉시 체결되는 자산으로 포트 하단을 먼저 깐다. 총자산 12%."
        }
      ]
    },
    {
      "date": "2026-07-15",
      "session": "kr",
      "comment": "반도체 +3% 반등은 추격 금지 — 대신 약세인 방어 우량주(삼성바이오)만 소액 편입. 어젯밤 예약한 미국 방어자산(헬스케어·금융·애플) 32M이 오늘 밤 체결되므로 현금은 48%대로 넉넉히 남긴다.",
      "placed": [
        {
          "action": "매수예약",
          "name": "삼성바이오로직스",
          "detail": "8,000,000원 · 다음 개장 시가 체결 대기 — 장기 계약 기반으로 이익이 꾸준한 국내 대표 방어 헬스케어 대형주. 오늘 -2.3%로 약세, 52주 고점 대비 -30%로 가격 메리트 구간이며 RSI 48.6으로 과열도 아니다. 반등을 추격하는 게 아니라 우량 방어주를 눌림에 담는 가치 접근 — 총자산 8%, 정수 5주 내외로 시작."
        },
        {
          "action": "유지",
          "name": "-",
          "detail": "삼성전자·SK하이닉스는 어제 이미 +3%대 급반등한 고변동 반도체라 추격 매수는 안정형 원칙에 어긋난다. 현대차·기아는 경기민감 약세, NAVER·카카오는 하락배열 성장주로 모두 회피. 지수가 20·60일선 아래 하락추세 내 되돌림 국면이라 신규 베팅보다 현금 방패(≈48%)를 지킨다. 예약된 미국 방어자산 체결을 먼저 확인한다."
        }
      ],
      "trades": []
    },
    {
      "date": "2026-07-15",
      "session": "fill",
      "comment": "예약 주문 개장 시가 체결",
      "placed": [],
      "trades": [
        {
          "action": "매수",
          "ticker": "XLV",
          "name": "헬스케어ETF",
          "krw": 11882199,
          "krw_str": "11,882,199",
          "qty": 50,
          "price_krw": 237644,
          "basis": "2026-07-14 개장 시가",
          "reason": "이익이 꾸준하고 경기·금리 민감도가 낮은 대표 방어 섹터. 반도체 쇼크가 국경 없이 번지는 장세에서 기술 대신 필수 수요주로 변동성을 낮춘다. ETF라 단일종목 리스크도 분산. 12%.",
          "placed_date": "2026-07-14"
        },
        {
          "action": "매수",
          "ticker": "XLF",
          "name": "금융ETF",
          "krw": 9923399,
          "krw_str": "9,923,399",
          "qty": 120,
          "price_krw": 82695,
          "basis": "2026-07-14 개장 시가",
          "reason": "JPM(EPS $6.14, 컨센 $5.85 대폭 상회)·WFC 실적 서프라이즈로 이익 모멘텀이 확인된 가치 섹터. 금리 급등이 NIM에 우호적이라 CPI가 뜨거워도 방어된다. 개별주 대신 ETF로 안전하게. 10%.",
          "placed_date": "2026-07-14"
        },
        {
          "action": "매수",
          "ticker": "AAPL",
          "name": "애플",
          "krw": 9796144,
          "krw_str": "9,796,144",
          "qty": 21,
          "price_krw": 466483,
          "basis": "2026-07-14 개장 시가",
          "reason": "재무가 탄탄하고 현금흐름이 꾸준한 초우량 대형주. 반도체·고베타 성장주가 밀린 날에도 +0.63%로 상대적 방어력을 보였다. 추격이 아닌 우량주 편입 차원의 소액 진입. 10%.",
          "placed_date": "2026-07-14"
        }
      ]
    }
  ],
  "history": [
    {
      "date": "2026-07-14",
      "total_value": 100000000,
      "total_value_str": "100,000,000",
      "return_pct": 0.0,
      "day_chg_pct": 0.0,
      "cash": 88000000,
      "asof": "개설일 시드",
      "holdings": [
        {
          "name": "금",
          "value_str": "12,000,000",
          "weight_pct": 12.0,
          "pl_pct": 0.0
        }
      ]
    }
  ],
  "updated": "2026-07-15",
  "total_value": 100035647,
  "holdings_value": 43637389,
  "return_pct": 0.04,
  "usdkrw": 1487.32,
  "holdings_view": [
    {
      "ticker": "GC=F",
      "name": "금",
      "qty": 1.9908,
      "unit": "oz",
      "currency": "USD",
      "cost_str": "12,000,000",
      "pl_krw_str": "+4,830",
      "avg_krw": 6027764,
      "avg_str": "6,027,764",
      "avg_native_str": "$4,034.02",
      "price_krw": 6030190,
      "price_str": "6,030,190",
      "price_native_str": "$4,054.40",
      "price_date": "2026-07-14",
      "value_krw": 12004830,
      "pl_pct": 0.04,
      "lots": [
        {
          "date": "2026-07-14",
          "session": "us",
          "qty": 1.9908,
          "price_krw": 6027764,
          "price_native": 4034.0,
          "currency": "USD",
          "krw": 12000000,
          "fx": 1494.24,
          "price_date": "2026-07-14",
          "basis": "즉시(24h)",
          "krw_str": "12,000,000",
          "price_krw_str": "6,027,764",
          "native_str": "$4,034.00"
        }
      ],
      "weight_pct": 12.0,
      "value_str": "12,004,830"
    },
    {
      "ticker": "XLV",
      "name": "헬스케어ETF",
      "qty": 50,
      "unit": "주",
      "currency": "USD",
      "cost_str": "11,882,199",
      "pl_krw_str": "-110,805",
      "avg_krw": 237644,
      "avg_str": "237,644",
      "avg_native_str": "$159.78",
      "price_krw": 235428,
      "price_str": "235,428",
      "price_native_str": "$158.29",
      "price_date": "2026-07-14",
      "value_krw": 11771394,
      "pl_pct": -0.93,
      "lots": [
        {
          "date": "2026-07-15",
          "session": "us",
          "qty": 50,
          "price_krw": 237644,
          "price_native": 159.78,
          "currency": "USD",
          "krw": 11882199,
          "fx": 1487.32,
          "price_date": "2026-07-14",
          "basis": "2026-07-14 개장 시가",
          "krw_str": "11,882,199",
          "price_krw_str": "237,644",
          "native_str": "$159.78"
        }
      ],
      "weight_pct": 11.8,
      "value_str": "11,771,394"
    },
    {
      "ticker": "XLF",
      "name": "금융ETF",
      "qty": 120,
      "unit": "주",
      "currency": "USD",
      "cost_str": "9,923,399",
      "pl_krw_str": "+103,517",
      "avg_krw": 82695,
      "avg_str": "82,695",
      "avg_native_str": "$55.60",
      "price_krw": 83558,
      "price_str": "83,558",
      "price_native_str": "$56.18",
      "price_date": "2026-07-14",
      "value_krw": 10026917,
      "pl_pct": 1.04,
      "lots": [
        {
          "date": "2026-07-15",
          "session": "us",
          "qty": 120,
          "price_krw": 82695,
          "price_native": 55.6,
          "currency": "USD",
          "krw": 9923399,
          "fx": 1487.32,
          "price_date": "2026-07-14",
          "basis": "2026-07-14 개장 시가",
          "krw_str": "9,923,399",
          "price_krw_str": "82,695",
          "native_str": "$55.60"
        }
      ],
      "weight_pct": 10.0,
      "value_str": "10,026,917"
    },
    {
      "ticker": "AAPL",
      "name": "애플",
      "qty": 21,
      "unit": "주",
      "currency": "USD",
      "cost_str": "9,796,144",
      "pl_krw_str": "+38,105",
      "avg_krw": 466483,
      "avg_str": "466,483",
      "avg_native_str": "$313.64",
      "price_krw": 468298,
      "price_str": "468,298",
      "price_native_str": "$314.86",
      "price_date": "2026-07-14",
      "value_krw": 9834249,
      "pl_pct": 0.39,
      "lots": [
        {
          "date": "2026-07-15",
          "session": "us",
          "qty": 21,
          "price_krw": 466483,
          "price_native": 313.64,
          "currency": "USD",
          "krw": 9796144,
          "fx": 1487.32,
          "price_date": "2026-07-14",
          "basis": "2026-07-14 개장 시가",
          "krw_str": "9,796,144",
          "price_krw_str": "466,483",
          "native_str": "$313.64"
        }
      ],
      "weight_pct": 9.8,
      "value_str": "9,834,249"
    }
  ],
  "pending_view": [
    {
      "placed_date": "2026-07-15",
      "session": "kr",
      "action": "buy",
      "ticker": "207940.KS",
      "name": "삼성바이오로직스",
      "krw": 8000000,
      "qty": null,
      "reason": "장기 계약 기반으로 이익이 꾸준한 국내 대표 방어 헬스케어 대형주. 오늘 -2.3%로 약세, 52주 고점 대비 -30%로 가격 메리트 구간이며 RSI 48.6으로 과열도 아니다. 반등을 추격하는 게 아니라 우량 방어주를 눌림에 담는 가치 접근 — 총자산 8%, 정수 5주 내외로 시작.",
      "min_fill_date": "2026-07-15",
      "krw_str": "8,000,000",
      "session_label": "🇰🇷 아침",
      "action_label": "매수"
    }
  ],
  "total_value_str": "100,035,647",
  "cash_str": "56,398,258",
  "holdings_value_str": "43,637,389",
  "start_capital_str": "100,000,000",
  "gain_str": "+35,647",
  "cash_weight_pct": 56.4,
  "day_chg_pct": 0.04,
  "days": 1,
  "priced_at": "2026-07-15T08:17:15+09:00",
  "eval_note": "일별 평가 확정 = 매일 18:00 KST (한국주 = 당일 종가 · 미국주 = 간밤 종가)",
  "persona": "stable",
  "persona_name": "안정형",
  "persona_emoji": "🛡️",
  "persona_tag": "가치·방어 — 저평가 우량주·배당, 현금 넉넉, 손실 최소 우선",
  "journal_view": [
    {
      "date": "2026-07-15",
      "session": "fill",
      "comment": "예약 주문 개장 시가 체결",
      "placed": [],
      "trades": [
        {
          "action": "매수",
          "ticker": "XLV",
          "name": "헬스케어ETF",
          "krw": 11882199,
          "krw_str": "11,882,199",
          "qty": 50,
          "price_krw": 237644,
          "basis": "2026-07-14 개장 시가",
          "reason": "이익이 꾸준하고 경기·금리 민감도가 낮은 대표 방어 섹터. 반도체 쇼크가 국경 없이 번지는 장세에서 기술 대신 필수 수요주로 변동성을 낮춘다. ETF라 단일종목 리스크도 분산. 12%.",
          "placed_date": "2026-07-14"
        },
        {
          "action": "매수",
          "ticker": "XLF",
          "name": "금융ETF",
          "krw": 9923399,
          "krw_str": "9,923,399",
          "qty": 120,
          "price_krw": 82695,
          "basis": "2026-07-14 개장 시가",
          "reason": "JPM(EPS $6.14, 컨센 $5.85 대폭 상회)·WFC 실적 서프라이즈로 이익 모멘텀이 확인된 가치 섹터. 금리 급등이 NIM에 우호적이라 CPI가 뜨거워도 방어된다. 개별주 대신 ETF로 안전하게. 10%.",
          "placed_date": "2026-07-14"
        },
        {
          "action": "매수",
          "ticker": "AAPL",
          "name": "애플",
          "krw": 9796144,
          "krw_str": "9,796,144",
          "qty": 21,
          "price_krw": 466483,
          "basis": "2026-07-14 개장 시가",
          "reason": "재무가 탄탄하고 현금흐름이 꾸준한 초우량 대형주. 반도체·고베타 성장주가 밀린 날에도 +0.63%로 상대적 방어력을 보였다. 추격이 아닌 우량주 편입 차원의 소액 진입. 10%.",
          "placed_date": "2026-07-14"
        }
      ]
    },
    {
      "date": "2026-07-15",
      "session": "kr",
      "comment": "반도체 +3% 반등은 추격 금지 — 대신 약세인 방어 우량주(삼성바이오)만 소액 편입. 어젯밤 예약한 미국 방어자산(헬스케어·금융·애플) 32M이 오늘 밤 체결되므로 현금은 48%대로 넉넉히 남긴다.",
      "placed": [
        {
          "action": "매수예약",
          "name": "삼성바이오로직스",
          "detail": "8,000,000원 · 다음 개장 시가 체결 대기 — 장기 계약 기반으로 이익이 꾸준한 국내 대표 방어 헬스케어 대형주. 오늘 -2.3%로 약세, 52주 고점 대비 -30%로 가격 메리트 구간이며 RSI 48.6으로 과열도 아니다. 반등을 추격하는 게 아니라 우량 방어주를 눌림에 담는 가치 접근 — 총자산 8%, 정수 5주 내외로 시작."
        },
        {
          "action": "유지",
          "name": "-",
          "detail": "삼성전자·SK하이닉스는 어제 이미 +3%대 급반등한 고변동 반도체라 추격 매수는 안정형 원칙에 어긋난다. 현대차·기아는 경기민감 약세, NAVER·카카오는 하락배열 성장주로 모두 회피. 지수가 20·60일선 아래 하락추세 내 되돌림 국면이라 신규 베팅보다 현금 방패(≈48%)를 지킨다. 예약된 미국 방어자산 체결을 먼저 확인한다."
        }
      ],
      "trades": []
    },
    {
      "date": "2026-07-14",
      "session": "us",
      "comment": "CPI 대기 밤 — 풀매수 금지. 방어자산(금·헬스케어)과 실적 확인된 가치(금융)·우량 대형주만 소액 분산, 현금 56% 방패 유지.",
      "placed": [
        {
          "action": "매수예약",
          "name": "헬스케어ETF",
          "detail": "12,000,000원 · 다음 개장 시가 체결 대기 — 이익이 꾸준하고 경기·금리 민감도가 낮은 대표 방어 섹터. 반도체 쇼크가 국경 없이 번지는 장세에서 기술 대신 필수 수요주로 변동성을 낮춘다. ETF라 단일종목 리스크도 분산. 12%."
        },
        {
          "action": "매수예약",
          "name": "금융ETF",
          "detail": "10,000,000원 · 다음 개장 시가 체결 대기 — JPM(EPS $6.14, 컨센 $5.85 대폭 상회)·WFC 실적 서프라이즈로 이익 모멘텀이 확인된 가치 섹터. 금리 급등이 NIM에 우호적이라 CPI가 뜨거워도 방어된다. 개별주 대신 ETF로 안전하게. 10%."
        },
        {
          "action": "매수예약",
          "name": "애플",
          "detail": "10,000,000원 · 다음 개장 시가 체결 대기 — 재무가 탄탄하고 현금흐름이 꾸준한 초우량 대형주. 반도체·고베타 성장주가 밀린 날에도 +0.63%로 상대적 방어력을 보였다. 추격이 아닌 우량주 편입 차원의 소액 진입. 10%."
        },
        {
          "action": "유지",
          "name": "-",
          "detail": "엔비디아·AMD·SMH 등 급락 반도체와 XLE(에너지 +3% 급등)는 모멘텀·고변동 구간이라 안정형 원칙상 신규 진입 회피. 나머지 56%는 21:30 CPI 코어 확인 후 방향이 서면 집행할 현금으로 남긴다."
        }
      ],
      "trades": [
        {
          "action": "매수",
          "ticker": "GC=F",
          "name": "금",
          "krw": 12000000,
          "krw_str": "12,000,000",
          "qty": 1.9908,
          "price_krw": 6027764,
          "basis": "즉시(24h)",
          "reason": "유가·구리·금 동반 상승의 리플레이션·지정학 프리미엄 국면. VIX 17.5로 언제든 튈 수 있는 이벤트(21:30 CPI) 앞에서 금은 순수 방패다. 즉시 체결되는 자산으로 포트 하단을 먼저 깐다. 총자산 12%."
        }
      ]
    }
  ],
  "history_view": [
    {
      "date": "2026-07-14",
      "total_value": 100000000,
      "total_value_str": "100,000,000",
      "return_pct": 0.0,
      "day_chg_pct": 0.0,
      "cash": 88000000,
      "asof": "개설일 시드",
      "holdings": [
        {
          "name": "금",
          "value_str": "12,000,000",
          "weight_pct": 12.0,
          "pl_pct": 0.0
        }
      ]
    }
  ]
}